adafruit_circuitpython_adafruitio-6.0.4.dist-info/licenses/LICENSE
adafruit_io/__init__.py
adafruit_io/adafruit_io.py
adafruit_io/adafruit_io_errors.py
adafruit_circuitpython_adafruitio-6.0.4.dist-info/METADATA
adafruit_circuitpython_adafruitio-6.0.4.dist-info/WHEEL
adafruit_circuitpython_adafruitio-6.0.4.dist-info/top_level.txt
adafruit_circuitpython_adafruitio-6.0.4.dist-info/RECORD
