Metadata-Version: 2.4
Name: adafruit-circuitpython-adafruitio
Version: 6.0.4
Summary: Adafruit IO for CircuitPython
Author-email: Adafruit Industries <circuitpython@adafruit.com>
License: MIT
Project-URL: Homepage, https://github.com/adafruit/Adafruit_CircuitPython_AdafruitIO
Keywords: adafruit,blinka,circuitpython,micropython,adafruit_io,adafruit-io,rest,api,iot,wifi
Classifier: Intended Audience :: Developers
Classifier: Topic :: Software Development :: Libraries
Classifier: Topic :: Software Development :: Embedded Systems
Classifier: Topic :: System :: Hardware
Classifier: License :: OSI Approved :: MIT License
Classifier: Programming Language :: Python :: 3
License-File: LICENSE
Requires-Dist: Adafruit-Blinka
Requires-Dist: adafruit-circuitpython-minimqtt
Provides-Extra: optional
Dynamic: license-file
